fast_tts/__init__.py
fast_tts/fast_tts.py
fast_tts/rvc/__init__.py
fast_tts/rvc/rvc_api.py
fast_tts/rvc/configs/__init__.py
fast_tts/rvc/configs/config.py
fast_tts/rvc/configs/v1/__init__.py
fast_tts/rvc/configs/v2/__init__.py
fast_tts/rvc/infer/__init__.py
fast_tts/rvc/infer/lib/__init__.py
fast_tts/rvc/infer/lib/audio.py
fast_tts/rvc/infer/lib/rmvpe.py
fast_tts/rvc/infer/lib/infer_pack/__init__.py
fast_tts/rvc/infer/lib/infer_pack/attentions.py
fast_tts/rvc/infer/lib/infer_pack/commons.py
fast_tts/rvc/infer/lib/infer_pack/models.py
fast_tts/rvc/infer/lib/infer_pack/modules.py
fast_tts/rvc/infer/lib/infer_pack/transforms.py
fast_tts/rvc/infer/lib/jit/__init__.py
fast_tts/rvc/infer/lib/jit/get_rmvpe.py
fast_tts/rvc/infer/modules/__init__.py
fast_tts/rvc/infer/modules/train/__init__.py
fast_tts/rvc/infer/modules/train/preprocess.py
fast_tts/rvc/infer/modules/vc/__init__.py
fast_tts/rvc/infer/modules/vc/modules.py
fast_tts/rvc/infer/modules/vc/pipeline.py
fast_tts/rvc/infer/modules/vc/utils.py
fast_tts/tortoise/__init__.py
fast_tts/tortoise/api_fast.py
fast_tts/tortoise/tortoise_api.py
fast_tts/tortoise/models/__init__.py
fast_tts/tortoise/models/activations.py
fast_tts/tortoise/models/arch_util.py
fast_tts/tortoise/models/autoregressive.py
fast_tts/tortoise/models/autoregressive_old.py
fast_tts/tortoise/models/bigvgan.py
fast_tts/tortoise/models/classifier.py
fast_tts/tortoise/models/clvp.py
fast_tts/tortoise/models/cvvp.py
fast_tts/tortoise/models/diffusion_decoder.py
fast_tts/tortoise/models/hifigan_decoder.py
fast_tts/tortoise/models/random_latent_generator.py
fast_tts/tortoise/models/stream_generator.py
fast_tts/tortoise/models/transformer.py
fast_tts/tortoise/models/vocoder.py
fast_tts/tortoise/models/xtransformers.py
fast_tts/tortoise/models/alias_free_torch/__init__.py
fast_tts/tortoise/models/alias_free_torch/act.py
fast_tts/tortoise/models/alias_free_torch/filter.py
fast_tts/tortoise/models/alias_free_torch/resample.py
fast_tts/tortoise/utils/__init__.py
fast_tts-0.0.3.dist-info/LICENSE
fast_tts-0.0.3.dist-info/METADATA
fast_tts-0.0.3.dist-info/WHEEL
fast_tts-0.0.3.dist-info/top_level.txt
fast_tts-0.0.3.dist-info/RECORD
